bdtariff/__init__.py
bdtariff-1.0.3.dist-info/METADATA
bdtariff-1.0.3.dist-info/WHEEL
bdtariff-1.0.3.dist-info/licenses/LICENSE
bdtariff-1.0.3.dist-info/RECORD
