Metadata-Version: 2.4
Name: bdtariff
Version: 1.0.3
Summary: Tariff rate and duty calculation based on Bangladesh Import and Export related H.S. Code
Project-URL: Homepage, https://github.com/nbrshamim/bdtariff
Project-URL: Issues, https://github.com/nbrshamim/bdtariff
Author-email: "Md.Shamim-Ul-Islam" <nbrshamim@gmail.com>
License-File: LICENSE
Classifier: License :: OSI Approved :: GNU General Public License v3 (GPLv3)
Classifier: Operating System :: OS Independent
Classifier: Programming Language :: Python :: 3
Requires-Python: >=3.8
Requires-Dist: requests
